cyjax_vectra_integration-1.2.0.data/scripts/cyjax-vectra-integration
src/__init__.py
src/cli.py
src/configuration.py
src/indicator_bulk_processor.py
src/indicator_enum.py
src/vectra_client.py
src/vectra_service.py
tests/__init__.py
tests/configuration_test.py
tests/indicator_bulk_processor_test.py
tests/vectra_client_test.py
tests/vectra_service_test.py
cyjax_vectra_integration-1.2.0.dist-info/METADATA
cyjax_vectra_integration-1.2.0.dist-info/WHEEL
cyjax_vectra_integration-1.2.0.dist-info/top_level.txt
cyjax_vectra_integration-1.2.0.dist-info/RECORD
