Metadata-Version: 2.1
Name: cyjax-vectra-integration
Version: 1.2.0
Summary: cyjax-vectra-integration provides an integration to send indicators to Vectra Brain.
Home-page: https://www.cyjax.com
Author: Cyjax Ltd.
Author-email: github@cyjax.com
License: MIT
Platform: UNKNOWN
Classifier: Development Status :: 5 - Production/Stable
Classifier: Environment :: Web Environment
Classifier: Intended Audience :: System Administrators
Classifier: License :: OSI Approved :: MIT License
Classifier: Operating System :: OS Independent
Classifier: Programming Language :: Python
Classifier: Programming Language :: Python :: 3
Classifier: Programming Language :: Python :: 3.6
Classifier: Programming Language :: Python :: 3.7
Classifier: Programming Language :: Python :: 3.8
Classifier: Programming Language :: Python :: 3.9
Classifier: Topic :: Utilities
Requires-Python: >=3.6
Requires-Dist: stix (==1.2.0.11)
Requires-Dist: cybox (==2.1.0.21)
Requires-Dist: requests (==2.25.1)
Requires-Dist: cyjax-cti (==1.0.7)
Provides-Extra: test
Requires-Dist: pytest ; extra == 'test'
Requires-Dist: pytest-mock ; extra == 'test'
Requires-Dist: flake8 ; extra == 'test'
Requires-Dist: pylint ; extra == 'test'
Requires-Dist: twine ; extra == 'test'
